simulant/__init__.py
simulant/os.py
simulant/display/__init__.py
simulant/display/panel.py
simulant/display/screen.py
simulant/display/utils/__init__.py
simulant/display/utils/element.py
simulant/display/utils/itr.py
simulant/display/window/__init__.py
simulant/display/window/location.py
simulant/display/window/size.py
simulant/keyboard/__init__.py
simulant/keyboard/key.py
simulant/mouse/__init__.py
simulant/mouse/human.py
simulant/shared/__init__.py
simulant/shared/exceptions.py
simulant-1.1.2.dist-info/METADATA
simulant-1.1.2.dist-info/WHEEL
simulant-1.1.2.dist-info/top_level.txt
simulant-1.1.2.dist-info/RECORD
